{
  "seller": [
    {
      "id": "b11c",
      "name": "sss",
      "email": "admin@admin.com",
      "password": "a"
    },
    {
      "id": "812f",
      "name": "aaa",
      "email": "admin@gmail.com",
      "password": "a"
    },
    {
      "id": "8b29",
      "name": "sss",
      "email": "q@q.com",
      "password": "1"
    },
    {
      "id": "c65d",
      "name": "sas",
      "email": "klajs",
      "password": "lkll"
    },
    {
      "id": "72db",
      "name": "Saqib",
      "email": "admin@admin.com",
      "password": "4545"
    },
    {
      "id": "06d2",
      "name": "aaa",
      "email": "tenant@tenant.com",
      "password": "dcdcdcdc"
    },
    {
      "id": "f0e1",
      "name": "ssss",
      "email": "tenant@tenant.comss",
      "password": "ssss"
    },
    {
      "id": "3db4",
      "name": "ssss",
      "email": "admin@admin.comaa",
      "password": "aaaa"
    },
    {
      "id": "9e97",
      "name": "sss",
      "email": "syedsaqibshah120@gmail.com",
      "password": "sss"
    },
    {
      "id": "e044",
      "name": "sss",
      "email": "admin@admin.comss",
      "password": "dwdw"
    },
    {
      "id": "6a38",
      "name": "ssss",
      "email": "admin@admin.com",
      "password": "a"
    }
  ]
}